pagseguro/__init__.py
pagseguro/admin.py
pagseguro/api.py
pagseguro/forms.py
pagseguro/models.py
pagseguro/settings.py
pagseguro/signals.py
pagseguro/urls.py
pagseguro/views.py
pagseguro/migrations/0001_initial.py
pagseguro/migrations/0002_auto_20150506_0220.py
pagseguro/migrations/0003_auto_20180127_1345.py
pagseguro/migrations/__init__.py
pagseguro/tests/__init__.py
pagseguro/tests/test_api.py
pagseguro/tests/test_models.py
pagseguro/tests/test_signals.py
pagseguro/tests/test_views.py
django_pagseguro2-4.0.0.dist-info/LICENSE
django_pagseguro2-4.0.0.dist-info/METADATA
django_pagseguro2-4.0.0.dist-info/WHEEL
django_pagseguro2-4.0.0.dist-info/top_level.txt
django_pagseguro2-4.0.0.dist-info/RECORD
