Metadata-Version: 2.1
Name: django-pagseguro2
Version: 4.0.0
Summary: Integração da API v2 do PagSeguro com o Django.
Home-page: https://github.com/allisson/django-pagseguro2
Author: Allisson Azevedo
Author-email: allisson@gmail.com
License: MIT
Classifier: Framework :: Django
Classifier: Intended Audience :: Developers
Classifier: Intended Audience :: System Administrators
Classifier: Operating System :: OS Independent
Classifier: Topic :: Software Development
Classifier: Programming Language :: Python :: 3.8
Classifier: Programming Language :: Python :: 3.9
Classifier: Programming Language :: Python :: 3.10
Classifier: Programming Language :: Python :: 3.11
License-File: LICENSE
Requires-Dist: Django (>=3.2)
Requires-Dist: requests
Requires-Dist: python-dateutil
Requires-Dist: xmltodict
